{
    "OBTResult": {
        "Env": {
            "BuildSystem": "Rocky_Linux_8_9",
            "Hardware": "CPU/Cores: 8, RAM: 15 GB",
            "IPAddress": "10.22.254.98 (OBT-AWS04)"
        },
        "BuildSet": {
            "Branch": "master",
            "BranchDate": "Thu Aug 21 19:38:25 2025 +0100",
            "BranchSHA": "dde0d2889f2feee133189e6da41f1417396c7198",
            "BuildType": "RelWithDebInfo",
            "Target": "BM/VM"
        },
        "Exclusion": {
            "Build": "MAKE_CASSANDRAEMBED, COUCHBASEEMBED, USE_AZURE, USE_AWS, WASMEMBED",
            "Documentation": "not built",
            "Unittest": "JlibReaderWriterTestTiming, AtomicTimingTest, AtomicTimingStressTest",
            "MLtest": "ClassicTestModified.ecl, SVCTest.ecl",
            "Regression": "embedded, 3rdparty, python2, wasmembed*"
        },
        "ThorConfig": {
            "Slaves": "4",
            "Channels": "1"
        },
        "Tasks": [
            {
                "Build": {
                    "Result": "PASSED",
                    "CMake": {
                        "Formatted": "11 sec (00:00:11)",
                        "RawSec": "11"
                    },
                    "Build": {
                        "Formatted": "841 sec (00:14:01)",
                        "RawSec": "841"
                    },
                    "Package": {
                        "Formatted": "229 sec (00:03:49)",
                        "RawSec": "229"
                    },
                    "Altogether": {
                        "Formatted": "1081 sec (00:18:01)",
                        "RawSec": "1081"
                    }
                }
            },
            {
                "Install": {
                    "Elaps": "No data"
                }
            },
            {
                "Unittests": {
                    "Result": "PASSED",
                    "Elaps": {
                        "Formatted": "2504 sec (00:41:44)",
                        "RawSec": "2504"
                    },
                    "Total": 490,
                    "Pass": 490,
                    "Fail": 0,
                    "Error": 0,
                    "Timeout": 0
                }
            },
            {
                "Wutooltests": {
                    "Result": "PASSED",
                    "Elaps": {
                        "Formatted": "1 sec (00:00:01)",
                        "RawSec": "1"
                    },
                    "Total": 19,
                    "Pass": 19,
                    "Fail": 0,
                    "Error": 0,
                    "Timeout": 0
                }
            },
            {
                "MLtests": {
                    "Result": "PASSED",
                    "DBSCAN": {
                        "Elaps": {
                            "Formatted": "10 sec  (00:00:10)",
                            "RawSec": "10"
                        },
                        "Total": 2,
                        "Pass": 2,
                        "Fail": 0,
                        "Result": "PASSED"
                    },
                    "GLM": {
                        "Elaps": {
                            "Formatted": "50 sec  (00:00:50)",
                            "RawSec": "50"
                        },
                        "Total": 7,
                        "Pass": 7,
                        "Fail": 0,
                        "Result": "PASSED"
                    },
                    "GNN": {
                        "Elaps": {
                            "Formatted": "68 sec  (00:01:08)",
                            "RawSec": "68"
                        },
                        "Total": 4,
                        "Pass": 4,
                        "Fail": 0,
                        "Result": "PASSED"
                    },
                    "KMeans": {
                        "Elaps": {
                            "Formatted": "4 sec  (00:00:04)",
                            "RawSec": "4"
                        },
                        "Total": 1,
                        "Pass": 1,
                        "Fail": 0,
                        "Result": "PASSED"
                    },
                    "LearningTrees": {
                        "Elaps": {
                            "Formatted": "169 sec  (00:02:49)",
                            "RawSec": "169"
                        },
                        "Total": 3,
                        "Pass": 3,
                        "Fail": 0,
                        "Result": "PASSED"
                    },
                    "PBblas": {
                        "Elaps": {
                            "Formatted": "12 sec  (00:00:12)",
                            "RawSec": "12"
                        },
                        "Total": 2,
                        "Pass": 2,
                        "Fail": 0,
                        "Result": "PASSED"
                    },
                    "SupportVectorMachines": {
                        "Elaps": {
                            "Formatted": "14 sec  (00:00:14)",
                            "RawSec": "14"
                        },
                        "Total": 1,
                        "Pass": 1,
                        "Fail": 0,
                        "Result": "PASSED"
                    },
                    "TextVectors": {
                        "Elaps": {
                            "Formatted": "10 sec  (00:00:10)",
                            "RawSec": "10"
                        },
                        "Total": 5,
                        "Pass": 5,
                        "Fail": 0,
                        "Result": "PASSED"
                    }
                }
            },
            {
                "Setup": {
                    "Result": "PASSED",
                    "hthor": {
                        "Elaps": {
                            "Formatted": "48 sec  (00:00:48)",
                            "RawSec": "48"
                        },
                        "Total": 9,
                        "Pass": 9,
                        "Fail": 0,
                        "Result": "PASSED"
                    },
                    "thor": {
                        "Elaps": {
                            "Formatted": "25 sec  (00:00:25)",
                            "RawSec": "25"
                        },
                        "Total": 9,
                        "Pass": 9,
                        "Fail": 0,
                        "Result": "PASSED"
                    },
                    "roxie": {
                        "Elaps": {
                            "Formatted": "44 sec  (00:00:44)",
                            "RawSec": "44"
                        },
                        "Total": 24,
                        "Pass": 24,
                        "Fail": 0,
                        "Result": "PASSED"
                    }
                }
            },
            {
                "Regress": {
                    "Result": "PASSED",
                    "Hthor": {
                        "Result": "PASSED",
                        "Elaps": {
                            "Formatted": "541 sec  (00:09:01)",
                            "RawSec": "541"
                        },
                        "Total": 1037,
                        "Pass": 1037,
                        "Fail": 0
                    },
                    "Thor": {
                        "Result": "PASSED",
                        "Elaps": {
                            "Formatted": "836 sec  (00:13:56)",
                            "RawSec": "836"
                        },
                        "Total": 920,
                        "Pass": 920,
                        "Fail": 0
                    },
                    "Roxie": {
                        "Result": "PASSED",
                        "Elaps": {
                            "Formatted": "676 sec  (00:11:16)",
                            "RawSec": "676"
                        },
                        "Total": 1129,
                        "Pass": 1129,
                        "Fail": 0
                    }
                }
            },
            {
                "Uninstall": {
                    "Elaps": "No data"
                }
            }
        ],
        "Errors": []
    }
}